{
    "_class": "page",
    "do_objectID": "7DF8B5F9-0638-4937-B9B9-B54BAF129F9D",
    "booleanOperation": -1,
    "isFixedToViewport": false,
    "isFlippedHorizontal": false,
    "isFlippedVertical": false,
    "isLocked": false,
    "isVisible": true,
    "layerListExpandedType": 0,
    "name": "Page 2",
    "nameIsFixed": false,
    "resizingConstraint": 63,
    "resizingType": 0,
    "rotation": 0,
    "shouldBreakMaskChain": false,
    "exportOptions": {
        "_class": "exportOptions",
        "includedLayerIds": [],
        "layerOptions": 0,
        "shouldTrim": false,
        "exportFormats": []
    },
    "frame": {
        "_class": "rect",
        "constrainProportions": false,
        "height": 0,
        "width": 0,
        "x": 0,
        "y": 0
    },
    "clippingMaskMode": 0,
    "hasClippingMask": false,
    "style": {
        "_class": "style",
        "do_objectID": "A3B6C2F5-3A64-4577-8A8F-EE1FED51A932",
        "endMarkerType": 0,
        "miterLimit": 10,
        "startMarkerType": 0,
        "windingRule": 1,
        "blur": {
            "_class": "blur",
            "isEnabled": false,
            "center": "{0.5, 0.5}",
            "motionAngle": 0,
            "radius": 10,
            "saturation": 1,
            "type": 0
        },
        "borderOptions": {
            "_class": "borderOptions",
            "isEnabled": true,
            "dashPattern": [],
            "lineCapStyle": 0,
            "lineJoinStyle": 0
        },
        "borders": [],
        "colorControls": {
            "_class": "colorControls",
            "isEnabled": false,
            "brightness": 0,
            "contrast": 1,
            "hue": 0,
            "saturation": 1
        },
        "contextSettings": {
            "_class": "graphicsContextSettings",
            "blendMode": 0,
            "opacity": 1
        },
        "fills": [],
        "innerShadows": [],
        "shadows": []
    },
    "hasClickThrough": true,
    "groupLayout": {
        "_class": "MSImmutableFreeformGroupLayout"
    },
    "layers": [
        {
            "_class": "artboard",
            "do_objectID": "2C934AF0-4E33-4FE5-A032-00363E925890",
            "booleanOperation": -1,
            "isFixedToViewport": false,
            "isFlippedHorizontal": false,
            "isFlippedVertical": false,
            "isLocked": false,
            "isVisible": true,
            "layerListExpandedType": 0,
            "name": "mac 15",
            "nameIsFixed": false,
            "resizingConstraint": 63,
            "resizingType": 0,
            "rotation": 0,
            "shouldBreakMaskChain": true,
            "exportOptions": {
                "_class": "exportOptions",
                "includedLayerIds": [],
                "layerOptions": 0,
                "shouldTrim": false,
                "exportFormats": []
            },
            "frame": {
                "_class": "rect",
                "constrainProportions": false,
                "height": 900,
                "width": 1440,
                "x": -694,
                "y": -451
            },
            "clippingMaskMode": 0,
            "hasClippingMask": false,
            "style": {
                "_class": "style",
                "do_objectID": "F43BBDF4-D0F3-483C-8243-FFF811A07FEE",
                "endMarkerType": 0,
                "miterLimit": 10,
                "startMarkerType": 0,
                "windingRule": 1,
                "blur": {
                    "_class": "blur",
                    "isEnabled": false,
                    "center": "{0.5, 0.5}",
                    "motionAngle": 0,
                    "radius": 10,
                    "saturation": 1,
                    "type": 0
                },
                "borderOptions": {
                    "_class": "borderOptions",
                    "isEnabled": true,
                    "dashPattern": [],
                    "lineCapStyle": 0,
                    "lineJoinStyle": 0
                },
                "borders": [],
                "colorControls": {
                    "_class": "colorControls",
                    "isEnabled": false,
                    "brightness": 0,
                    "contrast": 1,
                    "hue": 0,
                    "saturation": 1
                },
                "contextSettings": {
                    "_class": "graphicsContextSettings",
                    "blendMode": 0,
                    "opacity": 1
                },
                "fills": [],
                "innerShadows": [],
                "shadows": []
            },
            "hasClickThrough": false,
            "groupLayout": {
                "_class": "MSImmutableFreeformGroupLayout"
            },
            "layers": [],
            "hasBackgroundColor": false,
            "includeBackgroundColorInExport": true,
            "includeInCloudUpload": true,
            "isFlowHome": false,
            "presetDictionary": {
                "height": 900,
                "offersLandscapeVariant": 0,
                "name": "mac 15",
                "width": 1440,
                "allowResizedMatching": 0
            },
            "resizesContent": false,
            "backgroundColor": {
                "_class": "color",
                "alpha": 1,
                "blue": 1,
                "green": 1,
                "red": 1
            },
            "horizontalRulerData": {
                "_class": "rulerData",
                "base": 0,
                "guides": []
            },
            "verticalRulerData": {
                "_class": "rulerData",
                "base": 0,
                "guides": []
            }
        },
        {
            "_class": "bitmap",
            "do_objectID": "BB412A28-198E-4AA5-9C63-075078029A37",
            "booleanOperation": -1,
            "isFixedToViewport": false,
            "isFlippedHorizontal": false,
            "isFlippedVertical": false,
            "isLocked": false,
            "isVisible": true,
            "layerListExpandedType": 0,
            "name": "roadmap",
            "nameIsFixed": false,
            "resizingConstraint": 63,
            "resizingType": 0,
            "rotation": 0,
            "shouldBreakMaskChain": false,
            "exportOptions": {
                "_class": "exportOptions",
                "includedLayerIds": [],
                "layerOptions": 0,
                "shouldTrim": false,
                "exportFormats": []
            },
            "frame": {
                "_class": "rect",
                "constrainProportions": true,
                "height": 1080,
                "width": 1920,
                "x": -960,
                "y": -541
            },
            "clippingMaskMode": 0,
            "hasClippingMask": false,
            "style": {
                "_class": "style",
                "do_objectID": "02FDE261-3C80-4480-990F-6E557391D92B",
                "endMarkerType": 0,
                "miterLimit": 10,
                "startMarkerType": 0,
                "windingRule": 1,
                "blur": {
                    "_class": "blur",
                    "isEnabled": false,
                    "center": "{0.5, 0.5}",
                    "motionAngle": 0,
                    "radius": 10,
                    "saturation": 1,
                    "type": 0
                },
                "borderOptions": {
                    "_class": "borderOptions",
                    "isEnabled": true,
                    "dashPattern": [],
                    "lineCapStyle": 0,
                    "lineJoinStyle": 0
                },
                "borders": [],
                "colorControls": {
                    "_class": "colorControls",
                    "isEnabled": false,
                    "brightness": 0,
                    "contrast": 1,
                    "hue": 0,
                    "saturation": 1
                },
                "contextSettings": {
                    "_class": "graphicsContextSettings",
                    "blendMode": 0,
                    "opacity": 1
                },
                "fills": [],
                "innerShadows": [],
                "shadows": []
            },
            "clippingMask": "{{0, 0}, {1, 1}}",
            "fillReplacesImage": false,
            "image": {
                "_class": "MSJSONFileReference",
                "_ref_class": "MSImageData",
                "_ref": "images/d1f9e84ae033c76c63c9f630744632c9dd839ea6.png"
            },
            "intendedDPI": 72
        }
    ],
    "includeInCloudUpload": true,
    "horizontalRulerData": {
        "_class": "rulerData",
        "base": -452,
        "guides": []
    },
    "verticalRulerData": {
        "_class": "rulerData",
        "base": -367,
        "guides": []
    }
}
